remo/__init__.py
remo/annotation_utils.py
remo/api.py
remo/config.py
remo/sdk.py
remo/utils.py
remo/version.py
remo/viewer.py
remo/domain/__init__.py
remo/domain/annotation.py
remo/domain/annotation_set.py
remo/domain/class_encodings.py
remo/domain/dataset.py
remo/domain/image.py
remo/domain/task.py
remo/endpoints/__init__.py
remo/endpoints/backend.py
remo/endpoints/frontend.py
remo_python-0.1.14.dist-info/LICENSE.txt
remo_python-0.1.14.dist-info/METADATA
remo_python-0.1.14.dist-info/WHEEL
remo_python-0.1.14.dist-info/top_level.txt
remo_python-0.1.14.dist-info/RECORD
